download_image/__init__.py
download_image/utils.py
download_image-1.0.0.dist-info/METADATA
download_image-1.0.0.dist-info/RECORD
download_image-1.0.0.dist-info/WHEEL
download_image-1.0.0.dist-info/top_level.txt
